setup.py
src/auditlog/__init__.py
src/auditlog/admin.py
src/auditlog/apps.py
src/auditlog/compat.py
src/auditlog/diff.py
src/auditlog/filters.py
src/auditlog/middleware.py
src/auditlog/mixins.py
src/auditlog/models.py
src/auditlog/receivers.py
src/auditlog/registry.py
src/auditlog/management/__init__.py
src/auditlog/management/commands/__init__.py
src/auditlog/management/commands/auditlogflush.py
src/auditlog/migrations/0001_initial.py
src/auditlog/migrations/0002_auto_support_long_primary_keys.py
src/auditlog/migrations/0003_logentry_remote_addr.py
src/auditlog/migrations/0004_logentry_detailed_object_repr.py
src/auditlog/migrations/0005_logentry_additional_data_verbose_name.py
src/auditlog/migrations/0006_object_pk_index.py
src/auditlog/migrations/0007_object_pk_type.py
src/auditlog/migrations/0008_remove_logentry_additional_data.py
src/auditlog/migrations/0009_logentry_additional_data.py
src/auditlog/migrations/__init__.py
src/dj_rit_auditlog.egg-info/PKG-INFO
src/dj_rit_auditlog.egg-info/SOURCES.txt
src/dj_rit_auditlog.egg-info/dependency_links.txt
src/dj_rit_auditlog.egg-info/not-zip-safe
src/dj_rit_auditlog.egg-info/requires.txt
src/dj_rit_auditlog.egg-info/top_level.txt