Metadata-Version: 1.0
Name: dj-rit-auditlog
Version: 0.5.2
Summary: Audit log app for Django
Home-page: https://github.com/audiolion/dj-rit-auditlog
Author: Jan-Jelle Kester, Ryan Castner
Author-email: UNKNOWN
License: MIT
Platform: UNKNOWN
